devpi_api_client/__init__.py
devpi_api_client/api/__init__.py
devpi_api_client/api/auth.py
devpi_api_client/api/base.py
devpi_api_client/api/index.py
devpi_api_client/api/project.py
devpi_api_client/api/token.py
devpi_api_client/api/user.py
devpi_api_client/exceptions.py
devpi_api_client/models/__init__.py
devpi_api_client/models/base.py
devpi_api_client/models/index.py
devpi_api_client/models/project.py
devpi_api_client/models/token.py
devpi_api_client/models/user.py
devpi_api_client/v1/__init__.py
devpi_api_client/version.py
devpi_api_client-0.2.0.dist-info/METADATA
devpi_api_client-0.2.0.dist-info/WHEEL
devpi_api_client-0.2.0.dist-info/licenses/LICENSE
devpi_api_client-0.2.0.dist-info/RECORD
