Metadata-Version: 2.4
Name: devpi-api-client
Version: 0.2.0
Summary: High-level Python client for managing users, indexes, tokens, and packages on devpi servers.
License: MIT
License-File: LICENSE
Keywords: devpi,pypi,api,client,packaging
Author: ramos
Author-email: crqdev@gmail.com
Requires-Python: >=3.9
Classifier: Development Status :: 3 - Alpha
Classifier: Intended Audience :: Developers
Classifier: License :: OSI Approved :: MIT License
Classifier: Programming Language :: Python
Classifier: Programming Language :: Python :: 3
Classifier: Programming Language :: Python :: 3.9
Classifier: Programming Language :: Python :: 3.10
Classifier: Programming Language :: Python :: 3.11
Classifier: Programming Language :: Python :: 3.12
Classifier: Programming Language :: Python :: 3.13
Classifier: Topic :: Software Development :: Libraries :: Python Modules
Requires-Dist: pkginfo (>=1.12.1.2,<2.0.0.0)
Requires-Dist: pydantic (>=2.11.8,<3.0.0)
Requires-Dist: pymacaroons (>=0.13.0,<0.14.0)
Requires-Dist: requests (>=2.32.5,<3.0.0)
Project-URL: Documentation, https://github.com/ramos_admin/python-devpi-api-client/blob/main/docs/index.md
Project-URL: Homepage, https://github.com/ramos_admin/python-devpi-api-client
Project-URL: Repository, https://github.com/ramos_admin/python-devpi-api-client
Project-URL: changelog, https://github.com/ramos_admin/python-devpi-api-client/blob/main/CHANGELOG.md
